{
  "ok": true,
  "overallProgress": 100,
  "completed": 100,
  "remaining": 0,
  "localCertified": true,
  "releaseGate": "OPEN_LOCAL",
  "finalReadiness": "ready-local-100",
  "pages": [
    "/horizon-hub",
    "/workspace-router",
    "/evidence-vault",
    "/helix-core",
    "/signal-parliament",
    "/resilience-deck",
    "/observability-core",
    "/incident-center",
    "/playbook-os",
    "/revenue-os",
    "/compliance-ledger",
    "/ops-replay",
    "/connector-inspector",
    "/env-doctor",
    "/runtime-health",
    "/prism-core",
    "/memory-map",
    "/execution-forum",
    "/titan-core",
    "/war-room",
    "/infinity-matrix",
    "/memory-citadel"
  ],
  "commands": [
    "npm run tpm:horizon:once",
    "npm run tpm:horizon",
    "npm run tpm:helix:once",
    "npm run tpm:helix",
    "npm run tpm:master:once",
    "npm run tpm:observability:once",
    "npm run tpm:observability",
    "npm run tpm:enterprise:once",
    "npm run tpm:enterprise",
    "npm run tpm:runtimeops:once",
    "npm run tpm:runtimeops",
    "npm run tpm:prism:once",
    "npm run tpm:prism",
    "npm run tpm:titan:once",
    "npm run tpm:titan"
  ],
  "nextWave": [
    {
      "slug": "horizon-hub",
      "title": "horizon hub",
      "progress": 97,
      "stage": "ACTIVE",
      "status": "strong"
    },
    {
      "slug": "workspace-router",
      "title": "workspace router",
      "progress": 97,
      "stage": "ACTIVE",
      "status": "strong"
    },
    {
      "slug": "evidence-vault",
      "title": "evidence vault",
      "progress": 97,
      "stage": "ACTIVE",
      "status": "strong"
    },
    {
      "slug": "helix-core",
      "title": "helix core",
      "progress": 100,
      "stage": "ACTIVE",
      "status": "strong"
    },
    {
      "slug": "signal-parliament",
      "title": "signal parliament",
      "progress": 100,
      "stage": "ACTIVE",
      "status": "strong"
    },
    {
      "slug": "resilience-deck",
      "title": "resilience deck",
      "progress": 100,
      "stage": "ACTIVE",
      "status": "strong"
    },
    {
      "slug": "observability-core",
      "title": "observability core",
      "progress": 97,
      "stage": "ACTIVE",
      "status": "strong"
    },
    {
      "slug": "incident-center",
      "title": "incident center",
      "progress": 97,
      "stage": "ACTIVE",
      "status": "strong"
    },
    {
      "slug": "playbook-os",
      "title": "playbook os",
      "progress": 97,
      "stage": "ACTIVE",
      "status": "strong"
    },
    {
      "slug": "revenue-os",
      "title": "revenue os",
      "progress": 89,
      "stage": "ACTIVE",
      "status": "strong"
    },
    {
      "slug": "compliance-ledger",
      "title": "compliance ledger",
      "progress": 89,
      "stage": "ACTIVE",
      "status": "strong"
    },
    {
      "slug": "ops-replay",
      "title": "ops replay",
      "progress": 89,
      "stage": "ACTIVE",
      "status": "strong"
    },
    {
      "slug": "connector-inspector",
      "title": "connector inspector",
      "progress": 80,
      "stage": "ACTIVE",
      "status": "strong"
    },
    {
      "slug": "env-doctor",
      "title": "env doctor",
      "progress": 80,
      "stage": "ACTIVE",
      "status": "strong"
    },
    {
      "slug": "runtime-health",
      "title": "runtime health",
      "progress": 80,
      "stage": "ACTIVE",
      "status": "strong"
    },
    {
      "slug": "prism-core",
      "title": "prism core",
      "progress": 100,
      "stage": "ACTIVE",
      "status": "strong"
    },
    {
      "slug": "memory-map",
      "title": "memory map",
      "progress": 100,
      "stage": "ACTIVE",
      "status": "strong"
    },
    {
      "slug": "execution-forum",
      "title": "execution forum",
      "progress": 100,
      "stage": "ACTIVE",
      "status": "strong"
    },
    {
      "slug": "titan-core",
      "title": "titan core",
      "progress": 100,
      "stage": "ACTIVE",
      "status": "strong"
    },
    {
      "slug": "war-room",
      "title": "war room",
      "progress": 100,
      "stage": "ACTIVE",
      "status": "strong"
    },
    {
      "slug": "infinity-matrix",
      "title": "infinity matrix",
      "progress": 100,
      "stage": "ACTIVE",
      "status": "strong"
    },
    {
      "slug": "memory-citadel",
      "title": "memory citadel",
      "progress": 100,
      "stage": "ACTIVE",
      "status": "strong"
    }
  ],
  "horizonLayer": {
    "active": true,
    "layer": "HORIZON_HUB_WORKSPACE_ROUTER_EVIDENCE_VAULT",
    "progress": 97,
    "status": "ACTIVE",
    "time": "2026-04-08T22:57:09.769Z"
  },
  "externalDeployBlocked": true,
  "blockers": [
    "External GoDaddy deploy remains blocked by current hosting plan."
  ],
  "helixLayer": {
    "active": true,
    "layer": "HELIX_CORE_SIGNAL_PARLIAMENT_RESILIENCE_DECK",
    "progress": 100,
    "status": "ACTIVE",
    "time": "2026-04-08T22:57:09.820Z"
  },
  "observabilityLayer": {
    "active": true,
    "layer": "OBSERVABILITY_CORE_INCIDENT_CENTER_PLAYBOOK_OS",
    "progress": 97,
    "status": "ACTIVE",
    "time": "2026-04-08T22:57:09.850Z"
  },
  "enterpriseLayer": {
    "active": true,
    "layer": "REVENUE_OS_COMPLIANCE_LEDGER_OPS_REPLAY",
    "progress": 89,
    "status": "ACTIVE",
    "time": "2026-04-08T22:57:09.868Z"
  },
  "runtimeOpsLayer": {
    "active": true,
    "layer": "CONNECTOR_INSPECTOR_ENV_DOCTOR_RUNTIME_HEALTH",
    "progress": 80,
    "status": "ACTIVE",
    "time": "2026-04-08T22:57:09.902Z"
  },
  "infinityContinuation": "ACTIVE",
  "prismLayer": {
    "active": true,
    "layer": "PRISM_CORE_MEMORY_MAP_EXECUTION_FORUM",
    "progress": 100,
    "status": "ACTIVE",
    "time": "2026-04-08T22:57:16.500Z"
  },
  "titanLayer": {
    "active": true,
    "layer": "TITAN_CORE_WAR_ROOM_INFINITY_MATRIX_MEMORY_CITADEL",
    "progress": 100,
    "status": "ACTIVE",
    "time": "2026-04-08T22:57:17.772Z"
  },
  "infinityPostClosure": {
    "active": true,
    "mode": "LOCAL_100_CONTINUATION",
    "status": "ACTIVE",
    "continuity": 100,
    "precision": 100,
    "time": "2026-04-08T22:57:17.772Z"
  },
  "runtimeDepth": {
    "status": "MAX_INTERNAL",
    "protectedPages": 22,
    "protectedCommands": 15,
    "confidence": 100,
    "time": "2026-04-08T22:57:17.773Z"
  }
}