[
  {
    "id": "SNAP-FMOSRC3V",
    "label": "builder-cycle-15",
    "createdAt": "2026-04-08T02:48:29.371Z",
    "meta": {
      "cash": 100,
      "positions": 0,
      "orders": 0,
      "ledger": 0,
      "alerts": 0
    }
  },
  {
    "id": "SNAP-NRXJF369",
    "label": "builder-cycle-12",
    "createdAt": "2026-04-08T02:47:53.261Z",
    "meta": {
      "cash": 100,
      "positions": 0,
      "orders": 0,
      "ledger": 0,
      "alerts": 0
    }
  },
  {
    "id": "SNAP-J54OXOFX",
    "label": "builder-cycle-9",
    "createdAt": "2026-04-08T02:47:17.127Z",
    "meta": {
      "cash": 100,
      "positions": 0,
      "orders": 0,
      "ledger": 0,
      "alerts": 0
    }
  },
  {
    "id": "SNAP-9O5H5047",
    "label": "builder-cycle-6",
    "createdAt": "2026-04-08T02:46:41.022Z",
    "meta": {
      "cash": 100,
      "positions": 0,
      "orders": 0,
      "ledger": 0,
      "alerts": 0
    }
  },
  {
    "id": "SNAP-VBYS20F0",
    "label": "builder-cycle-3",
    "createdAt": "2026-04-08T02:46:04.879Z",
    "meta": {
      "cash": 100,
      "positions": 0,
      "orders": 0,
      "ledger": 0,
      "alerts": 0
    }
  },
  {
    "id": "SNAP-5E82BE73",
    "label": "builder-cycle-30",
    "createdAt": "2026-04-08T02:45:39.023Z",
    "meta": {
      "cash": 100,
      "positions": 0,
      "orders": 0,
      "ledger": 0,
      "alerts": 0
    }
  },
  {
    "id": "SNAP-4W8ORCBD",
    "label": "builder-cycle-27",
    "createdAt": "2026-04-08T02:45:02.918Z",
    "meta": {
      "cash": 100,
      "positions": 0,
      "orders": 0,
      "ledger": 0,
      "alerts": 0
    }
  },
  {
    "id": "SNAP-2YNM6Y00",
    "label": "builder-cycle-24",
    "createdAt": "2026-04-08T02:44:26.840Z",
    "meta": {
      "cash": 100,
      "positions": 0,
      "orders": 0,
      "ledger": 0,
      "alerts": 0
    }
  },
  {
    "id": "SNAP-I8O5WKK8",
    "label": "builder-cycle-21",
    "createdAt": "2026-04-08T02:43:50.729Z",
    "meta": {
      "cash": 100,
      "positions": 0,
      "orders": 0,
      "ledger": 0,
      "alerts": 0
    }
  },
  {
    "id": "SNAP-VKYCBL3A",
    "label": "builder-cycle-18",
    "createdAt": "2026-04-08T02:43:14.640Z",
    "meta": {
      "cash": 100,
      "positions": 0,
      "orders": 0,
      "ledger": 0,
      "alerts": 0
    }
  },
  {
    "id": "SNAP-A0NMX235",
    "label": "builder-cycle-15",
    "createdAt": "2026-04-08T02:42:38.515Z",
    "meta": {
      "cash": 100,
      "positions": 0,
      "orders": 0,
      "ledger": 0,
      "alerts": 0
    }
  },
  {
    "id": "SNAP-MVFGXWKU",
    "label": "builder-cycle-12",
    "createdAt": "2026-04-08T02:42:02.426Z",
    "meta": {
      "cash": 100,
      "positions": 0,
      "orders": 0,
      "ledger": 0,
      "alerts": 0
    }
  },
  {
    "id": "SNAP-AO73SOHC",
    "label": "builder-cycle-9",
    "createdAt": "2026-04-08T02:41:26.309Z",
    "meta": {
      "cash": 100,
      "positions": 0,
      "orders": 0,
      "ledger": 0,
      "alerts": 0
    }
  },
  {
    "id": "SNAP-EHQ2HQAV",
    "label": "builder-cycle-6",
    "createdAt": "2026-04-08T02:40:50.217Z",
    "meta": {
      "cash": 100,
      "positions": 0,
      "orders": 0,
      "ledger": 0,
      "alerts": 0
    }
  },
  {
    "id": "SNAP-5TFADMSS",
    "label": "builder-cycle-3",
    "createdAt": "2026-04-08T02:40:14.087Z",
    "meta": {
      "cash": 100,
      "positions": 0,
      "orders": 0,
      "ledger": 0,
      "alerts": 0
    }
  },
  {
    "id": "SNAP-62WNSVBT",
    "label": "builder-cycle-21",
    "createdAt": "2026-04-08T01:58:29.686Z",
    "meta": {
      "cash": 100,
      "positions": 0,
      "orders": 0,
      "ledger": 0,
      "alerts": 0
    }
  },
  {
    "id": "SNAP-WUSTCSV5",
    "label": "builder-cycle-18",
    "createdAt": "2026-04-08T01:57:53.634Z",
    "meta": {
      "cash": 100,
      "positions": 0,
      "orders": 0,
      "ledger": 0,
      "alerts": 0
    }
  },
  {
    "id": "SNAP-URNU4972",
    "label": "builder-cycle-15",
    "createdAt": "2026-04-08T01:57:17.604Z",
    "meta": {
      "cash": 100,
      "positions": 0,
      "orders": 0,
      "ledger": 0,
      "alerts": 0
    }
  },
  {
    "id": "SNAP-6OXJ6SB2",
    "label": "builder-cycle-12",
    "createdAt": "2026-04-08T01:56:41.558Z",
    "meta": {
      "cash": 100,
      "positions": 0,
      "orders": 0,
      "ledger": 0,
      "alerts": 0
    }
  },
  {
    "id": "SNAP-VKWDJ5XD",
    "label": "builder-cycle-9",
    "createdAt": "2026-04-08T01:56:05.520Z",
    "meta": {
      "cash": 100,
      "positions": 0,
      "orders": 0,
      "ledger": 0,
      "alerts": 0
    }
  },
  {
    "id": "SNAP-R2T2IRV0",
    "label": "builder-cycle-6",
    "createdAt": "2026-04-08T01:55:29.491Z",
    "meta": {
      "cash": 100,
      "positions": 0,
      "orders": 0,
      "ledger": 0,
      "alerts": 0
    }
  },
  {
    "id": "SNAP-CGSUUV1N",
    "label": "builder-cycle-3",
    "createdAt": "2026-04-08T01:54:53.459Z",
    "meta": {
      "cash": 100,
      "positions": 0,
      "orders": 0,
      "ledger": 0,
      "alerts": 0
    }
  },
  {
    "id": "SNAP-OLHBYK6X",
    "label": "builder-cycle-24",
    "createdAt": "2026-04-08T01:54:20.185Z",
    "meta": {
      "cash": 100,
      "positions": 0,
      "orders": 0,
      "ledger": 0,
      "alerts": 0
    }
  },
  {
    "id": "SNAP-99P1ZYTU",
    "label": "builder-cycle-21",
    "createdAt": "2026-04-08T01:53:44.143Z",
    "meta": {
      "cash": 100,
      "positions": 0,
      "orders": 0,
      "ledger": 0,
      "alerts": 0
    }
  },
  {
    "id": "SNAP-SUBMYU7L",
    "label": "builder-cycle-18",
    "createdAt": "2026-04-08T01:53:08.112Z",
    "meta": {
      "cash": 100,
      "positions": 0,
      "orders": 0,
      "ledger": 0,
      "alerts": 0
    }
  }
]